sat/__init__.py
smolagentstelegram-1.0.1.dist-info/METADATA
smolagentstelegram-1.0.1.dist-info/WHEEL
smolagentstelegram-1.0.1.dist-info/top_level.txt
smolagentstelegram-1.0.1.dist-info/RECORD
