Metadata-Version: 2.2
Name: SmolAgentsTelegram
Version: 1.0.1
Summary: Wrapper To Create Telegram Agent Written in Small Agents Framework
Author: Viacheslav Kovalevskyi
Author-email: viacheslav@kovalevskyi.com
License: MIT
Requires-Dist: smolagents==1.12
Requires-Dist: python-dotenv==1.1
Requires-Dist: python-telegram-bot==22
Dynamic: author
Dynamic: author-email
Dynamic: description
Dynamic: description-content-type
Dynamic: license
Dynamic: requires-dist
Dynamic: summary
